agent_validator/__init__.py
agent_validator/config.py
agent_validator/errors.py
agent_validator/logging_.py
agent_validator/redact.py
agent_validator/retry.py
agent_validator/schemas.py
agent_validator/typing_.py
agent_validator/validate.py
agent_validator/version.py
agent_validator-1.0.0.dist-info/licenses/LICENSE
cli/__init__.py
cli/main.py
agent_validator-1.0.0.dist-info/METADATA
agent_validator-1.0.0.dist-info/WHEEL
agent_validator-1.0.0.dist-info/entry_points.txt
agent_validator-1.0.0.dist-info/top_level.txt
agent_validator-1.0.0.dist-info/RECORD
