Metadata-Version: 2.4
Name: agent-validator
Version: 1.0.0
Summary: A library for validating agent outputs against schemas
Author-email: Neil Okikiolu <neil@agentvalidator.dev>
License: MIT
Project-URL: Homepage, https://github.com/agent-validator/agent-validator
Project-URL: Documentation, https://agent-validator.readthedocs.io/
Project-URL: Repository, https://github.com/agent-validator/agent-validator
Project-URL: Bug Tracker, https://github.com/agent-validator/agent-validator/issues
Keywords: validation,schema,agent,ai
Classifier: Development Status :: 3 - Alpha
Classifier: Intended Audience :: Developers
Classifier: License :: OSI Approved :: MIT License
Classifier: Programming Language :: Python :: 3
Classifier: Programming Language :: Python :: 3.9
Classifier: Programming Language :: Python :: 3.10
Classifier: Programming Language :: Python :: 3.11
Classifier: Programming Language :: Python :: 3.12
Requires-Python: >=3.9
License-File: LICENSE
Requires-Dist: requests>=2.25.0
Requires-Dist: typer>=0.9.0
Requires-Dist: tomli>=2.0.0; python_version < "3.11"
Provides-Extra: dev
Requires-Dist: black>=23.0.0; extra == "dev"
Requires-Dist: ruff>=0.1.0; extra == "dev"
Requires-Dist: mypy>=1.0.0; extra == "dev"
Requires-Dist: types-requests>=2.25.0; extra == "dev"
Requires-Dist: build>=1.0.0; extra == "dev"
Requires-Dist: twine>=4.0.0; extra == "dev"
Provides-Extra: test
Requires-Dist: pytest>=7.0.0; extra == "test"
Requires-Dist: pytest-cov>=4.0.0; extra == "test"
Requires-Dist: hypothesis>=6.0.0; extra == "test"
Requires-Dist: pytest-mock>=3.0.0; extra == "test"
Requires-Dist: pytest-asyncio>=0.21.0; extra == "test"
Dynamic: license-file
